{"id2label": {"0": "littin1", "1": "grhcha1", "2": "colcha1", "3": "compau", "4": "compot1", "5": "buvhum1", "6": "stvhum2", "7": "rtlhum", "8": "andeme1", "9": "squcuc1", "10": "rebpig1", "11": "whtdov", "12": "gycwor1", "13": "roahaw", "14": "gryhaw2", "15": "trsowl", "16": "rinkin1", "17": "bucmot2", "18": "higmot1", "19": "rehbar1", "20": "kebtou1", "21": "acowoo", "22": "hofwoo1", "23": "linwoo1", "24": "yehcar1", "25": "laufal1", "26": "orcpar", "27": "whcpar", "28": "brwpar1", "29": "whfpar1", "30": "orfpar", "31": "crfpar", "32": "oliwoo1", "33": "sthwoo1", "34": "azaspi1", "35": "yebela1", "36": "goftyr1", "37": "cotfly1", "38": "wewpew", "39": "rumfly1", "40": "socfly1", "41": "grekis", "42": "bobfly1", "43": "trokin", "44": "ducfly", "45": "lotman1", "46": "mastit1", "47": "rotbec", "48": "yetvir", "49": "blcjay1", "50": "grnjay", "51": "brnjay", "52": "melwar1", "53": "runwre1", "54": "whiwre1", "55": "rubwre1", "56": "rawwre1", "57": "plawre1", "58": "houwre", "59": "andsol1", "60": "clcrob", "61": "yeceup1", "62": "yeteup1", "63": "ccbfin", "64": "rucspa1", "65": "wegspa1", "66": "pregrs2", "67": "ruboro1", "68": "monoro1", "69": "yebori1", "70": "melbla1", "71": "grtgra", "72": "tenwar", "73": "yelwar", "74": "rucwar1", "75": "rucwar", "76": "sltred", "77": "rcatan1", "78": "strsal1", "79": "butsal1", "80": "blhsal1", "81": "banana", "82": "yefgra1", "83": "flrtan1", "84": "sibtan2", "85": "bugtan", "86": "blctan1", "87": "scrtan1", "88": "obnthr1"}, "label2id": {"littin1": 0, "grhcha1": 1, "colcha1": 2, "compau": 3, "compot1": 4, "buvhum1": 5, "stvhum2": 6, "rtlhum": 7, "andeme1": 8, "squcuc1": 9, "rebpig1": 10, "whtdov": 11, "gycwor1": 12, "roahaw": 13, "gryhaw2": 14, "trsowl": 15, "rinkin1": 16, "bucmot2": 17, "higmot1": 18, "rehbar1": 19, "kebtou1": 20, "acowoo": 21, "hofwoo1": 22, "linwoo1": 23, "yehcar1": 24, "laufal1": 25, "orcpar": 26, "whcpar": 27, "brwpar1": 28, "whfpar1": 29, "orfpar": 30, "crfpar": 31, "oliwoo1": 32, "sthwoo1": 33, "azaspi1": 34, "yebela1": 35, "goftyr1": 36, "cotfly1": 37, "wewpew": 38, "rumfly1": 39, "socfly1": 40, "grekis": 41, "bobfly1": 42, "trokin": 43, "ducfly": 44, "lotman1": 45, "mastit1": 46, "rotbec": 47, "yetvir": 48, "blcjay1": 49, "grnjay": 50, "brnjay": 51, "melwar1": 52, "runwre1": 53, "whiwre1": 54, "rubwre1": 55, "rawwre1": 56, "plawre1": 57, "houwre": 58, "andsol1": 59, "clcrob": 60, "yeceup1": 61, "yeteup1": 62, "ccbfin": 63, "rucspa1": 64, "wegspa1": 65, "pregrs2": 66, "ruboro1": 67, "monoro1": 68, "yebori1": 69, "melbla1": 70, "grtgra": 71, "tenwar": 72, "yelwar": 73, "rucwar1": 74, "rucwar": 75, "sltred": 76, "rcatan1": 77, "strsal1": 78, "butsal1": 79, "blhsal1": 80, "banana": 81, "yefgra1": 82, "flrtan1": 83, "sibtan2": 84, "bugtan": 85, "blctan1": 86, "scrtan1": 87, "obnthr1": 88}}